maspim/__init__.py
maspim/data/__init__.py
maspim/data/age_model.py
maspim/data/annotating.py
maspim/data/combine_feature_tables.py
maspim/data/helpers.py
maspim/data/main.py
maspim/data/msi.py
maspim/data/test_cwt.py
maspim/data/test_unsharpen_sharpen.py
maspim/data/test_zone_averages.py
maspim/data/xrf.py
maspim/exporting/__init__.py
maspim/exporting/from_mcf/__init__.py
maspim/exporting/from_mcf/helper.py
maspim/exporting/from_mcf/rtms_communicator.py
maspim/exporting/from_mcf/spectrum.py
maspim/exporting/from_mcf/test_calibration.py
maspim/exporting/from_mcf/test_r_find_home.py
maspim/exporting/from_sqlite/__init__.py
maspim/exporting/from_sqlite/calibration.py
maspim/exporting/from_sqlite/func.py
maspim/exporting/from_sqlite/parser.py
maspim/exporting/legacy/__init__.py
maspim/exporting/legacy/data_analysis_export.py
maspim/exporting/legacy/ion_image.py
maspim/exporting/legacy/parser.py
maspim/exporting/sqlite_mcf_communicator/__init__.py
maspim/exporting/sqlite_mcf_communicator/hdf.py
maspim/exporting/sqlite_mcf_communicator/sql_to_mcf.py
maspim/imaging/__init__.py
maspim/imaging/interactive.py
maspim/imaging/main.py
maspim/imaging/learning/__init__.py
maspim/imaging/learning/synthetic_images.py
maspim/imaging/misc/__init__.py
maspim/imaging/misc/find_punch_holes.py
maspim/imaging/misc/fit_distorted_rectangle.py
maspim/imaging/register/__init__.py
maspim/imaging/register/descriptor.py
maspim/imaging/register/feature_descriptor.py
maspim/imaging/register/finding_global_shift.py
maspim/imaging/register/helpers.py
maspim/imaging/register/my_hog.py
maspim/imaging/register/test_auto_align.py
maspim/imaging/register/test_calc_shift_vectors.py
maspim/imaging/register/test_combine.py
maspim/imaging/register/test_descriptor.py
maspim/imaging/register/test_df_trafo.py
maspim/imaging/register/test_hog.py
maspim/imaging/register/test_tracer.py
maspim/imaging/register/transformation.py
maspim/imaging/test/__init__.py
maspim/imaging/test/test_directionality_image.py
maspim-1.4.2.dist-info/LICENSE
maspim-1.4.2.dist-info/METADATA
maspim-1.4.2.dist-info/WHEEL
maspim-1.4.2.dist-info/top_level.txt
maspim-1.4.2.dist-info/RECORD
