Metadata-Version: 2.2
Name: maspim
Version: 1.4.2
Summary: Processing of mass spectrometry imaging and micro X-Ray fluorescence data.
Home-page: https://github.com/yaza11/maspim
Author: Yannick Zander
Author-email: yzander@marum.de
Keywords: python,mass spectrometry imaging,bruker,mcf,MALDI,laminated,lamination,image registration
Classifier: Programming Language :: Python :: 3
Classifier: License :: OSI Approved :: MIT License
Classifier: Operating System :: Unix
Classifier: Operating System :: MacOS :: MacOS X
Classifier: Operating System :: Microsoft :: Windows
License-File: LICENSE
Requires-Dist: matplotlib
Requires-Dist: numpy
Requires-Dist: pandas
Requires-Dist: scipy
Requires-Dist: tqdm
Requires-Dist: opencv-python
Requires-Dist: scikit-learn
Requires-Dist: scikit-image
Requires-Dist: psutil
Requires-Dist: h5py
Requires-Dist: pillow
Requires-Dist: textdistance
Requires-Dist: astropy
Requires-Dist: mfe
Provides-Extra: dev
Requires-Dist: twine; extra == "dev"
Provides-Extra: all
Requires-Dist: rpy2==3.5.12; extra == "all"
Dynamic: author
Dynamic: author-email
Dynamic: classifier
Dynamic: description
Dynamic: description-content-type
Dynamic: home-page
Dynamic: keywords
Dynamic: provides-extra
Dynamic: requires-dist
Dynamic: summary
